README.rst
ermes.py
setup.py
Ermes.egg-info/PKG-INFO
Ermes.egg-info/SOURCES.txt
Ermes.egg-info/dependency_links.txt
Ermes.egg-info/top_level.txt