Metadata-Version: 1.1
Name: Ermes
Version: 0.1a
Summary: Socks5 proxy client for Python
Home-page: UNKNOWN
Author: Cosmia Fu
Author-email: cosmiafu@gmail.com
License: ISC
Platform: UNKNOWN
Classifier: Development Status :: 2 - Pre-Alpha
Classifier: Environment :: Web Environment
Classifier: Intended Audience :: Developers
Classifier: License :: OSI Approved :: ISC License (ISCL)
Classifier: Operating System :: OS Independent
Classifier: Programming Language :: Python
